marpdown/__init__.py
marpdown/css.py
marpdown/ppt.py
marpdown/slide.py
marpdown/utils.py
marpdown/writer.py
marpdown-0.7.0.dist-info/LICENSE
marpdown-0.7.0.dist-info/METADATA
marpdown-0.7.0.dist-info/WHEEL
marpdown-0.7.0.dist-info/top_level.txt
marpdown-0.7.0.dist-info/RECORD
